Metadata-Version: 2.1
Name: tiny-storage-unstable-unstable
Version: 1.1.0
Summary: Tiny library for key-value single-file application data storage
Home-page: https://github.com/girvel/tiny_storage
Author: Nikita Girvel Dobrynin
Author-email: widauka@ya.ru
Classifier: Programming Language :: Python :: 3
Classifier: License :: OSI Approved :: MIT License
Classifier: Operating System :: OS Independent
Requires-Python: >=3.6
Requires-Dist: PyYAML (>=5.3.1)
